qtreload/__init__.py
qtreload/_version.py
qtreload/install.py
qtreload/py.typed
qtreload/pydevd_reload.py
qtreload/qt_reload.py
qtreload/utilities.py
qtreload-0.2.3.dist-info/LICENSE
qtreload-0.2.3.dist-info/METADATA
qtreload-0.2.3.dist-info/WHEEL
qtreload-0.2.3.dist-info/top_level.txt
qtreload-0.2.3.dist-info/RECORD
