Metadata-Version: 2.2
Name: qtreload
Version: 0.2.3
Summary: Qt utilities to enable hot-reloading of python/Qt code
Author-email: "Lukasz G. Migas" <lukas.migas@yahoo.com>
License: BSD 3-Clause License
Project-URL: homepage, https://github.com/lukasz-migas/qtreload
Project-URL: repository, https://github.com/lukasz-migas/qtreload
Classifier: Development Status :: 3 - Alpha
Classifier: License :: OSI Approved :: BSD License
Classifier: Natural Language :: English
Classifier: Programming Language :: Python :: 3
Classifier: Programming Language :: Python :: 3.8
Classifier: Programming Language :: Python :: 3.9
Classifier: Programming Language :: Python :: 3.10
Classifier: Programming Language :: Python :: 3.11
Classifier: Typing :: Typed
Requires-Python: >=3.8
License-File: LICENSE
Requires-Dist: qtpy
Requires-Dist: superqt
Provides-Extra: test
Requires-Dist: pytest>=6.0; extra == "test"
Requires-Dist: pytest-cov; extra == "test"
Requires-Dist: pytest-qt; extra == "test"
Provides-Extra: pyside2
Requires-Dist: pyside2; extra == "pyside2"
Provides-Extra: pyside6
Requires-Dist: pyside6; extra == "pyside6"
Provides-Extra: pyqt5
Requires-Dist: pyqt5; extra == "pyqt5"
Provides-Extra: pyqt6
Requires-Dist: pyqt6; extra == "pyqt6"
Provides-Extra: dev
Requires-Dist: black; extra == "dev"
Requires-Dist: ipython; extra == "dev"
Requires-Dist: mypy; extra == "dev"
Requires-Dist: pdbpp; extra == "dev"
Requires-Dist: pre-commit; extra == "dev"
Requires-Dist: rich; extra == "dev"
Requires-Dist: ruff; extra == "dev"
Requires-Dist: qtreload[test]; extra == "dev"
